main.py
src/__init__.py
src/generator.py
src/package_info.py
src/parsers.py
src/utils.py
src/compatibility_checkers/__init__.py
src/compatibility_checkers/base.py
src/compatibility_checkers/fast_checker.py
src/compatibility_checkers/installation_checker.py
flexible_requirements-0.1.6.dist-info/METADATA
flexible_requirements-0.1.6.dist-info/WHEEL
flexible_requirements-0.1.6.dist-info/entry_points.txt
flexible_requirements-0.1.6.dist-info/top_level.txt
flexible_requirements-0.1.6.dist-info/RECORD
