Metadata-Version: 2.1
Name: flexible-requirements
Version: 0.1.6
Summary: A library for generating flexible Python requirements
Home-page: https://github.com/benny-png/Flexible-Requirements-python-LIBRARY
Author: benny-png
Author-email: mazikuben2@gmail.com
License: UNKNOWN
Platform: UNKNOWN
Classifier: Programming Language :: Python :: 3
Classifier: License :: OSI Approved :: MIT License
Classifier: Operating System :: OS Independent
Requires-Python: >=3.6
Requires-Dist: packaging
Requires-Dist: requests
